{
	"configurations" : 
	[
		{
			"directories" : 
			[
				{
					"build" : ".",
					"jsonFile" : "directory-.-Debug-f5ebdc15457944623624.json",
					"minimumCMakeVersion" : 
					{
						"string" : "3.14"
					},
					"projectIndex" : 0,
					"source" : ".",
					"targetIndexes" : 
					[
						0,
						1,
						2,
						3,
						4,
						5,
						6
					]
				}
			],
			"name" : "Debug",
			"projects" : 
			[
				{
					"directoryIndexes" : 
					[
						0
					],
					"name" : "SimiLangCompiler",
					"targetIndexes" : 
					[
						0,
						1,
						2,
						3,
						4,
						5,
						6
					]
				}
			],
			"targets" : 
			[
				{
					"directoryIndex" : 0,
					"id" : "AArch64TargetParserTableGen::@6890427a1f51a3e7e1df",
					"jsonFile" : "target-AArch64TargetParserTableGen-Debug-49fd5271d3474d98a143.json",
					"name" : "AArch64TargetParserTableGen",
					"projectIndex" : 0
				},
				{
					"directoryIndex" : 0,
					"id" : "ARMTargetParserTableGen::@6890427a1f51a3e7e1df",
					"jsonFile" : "target-ARMTargetParserTableGen-Debug-835b44b3e33f3b93bf65.json",
					"name" : "ARMTargetParserTableGen",
					"projectIndex" : 0
				},
				{
					"directoryIndex" : 0,
					"id" : "RISCVTargetParserTableGen::@6890427a1f51a3e7e1df",
					"jsonFile" : "target-RISCVTargetParserTableGen-Debug-10d591326a8f2870e142.json",
					"name" : "RISCVTargetParserTableGen",
					"projectIndex" : 0
				},
				{
					"directoryIndex" : 0,
					"id" : "SimiLangCompiler::@6890427a1f51a3e7e1df",
					"jsonFile" : "target-SimiLangCompiler-Debug-906883bc3ed8ccae99ee.json",
					"name" : "SimiLangCompiler",
					"projectIndex" : 0
				},
				{
					"directoryIndex" : 0,
					"id" : "acc_gen::@6890427a1f51a3e7e1df",
					"jsonFile" : "target-acc_gen-Debug-054c2120f5b91d8365d8.json",
					"name" : "acc_gen",
					"projectIndex" : 0
				},
				{
					"directoryIndex" : 0,
					"id" : "intrinsics_gen::@6890427a1f51a3e7e1df",
					"jsonFile" : "target-intrinsics_gen-Debug-5aafb9103aa30beb213f.json",
					"name" : "intrinsics_gen",
					"projectIndex" : 0
				},
				{
					"directoryIndex" : 0,
					"id" : "omp_gen::@6890427a1f51a3e7e1df",
					"jsonFile" : "target-omp_gen-Debug-16e73e07085f3d4ec4cc.json",
					"name" : "omp_gen",
					"projectIndex" : 0
				}
			]
		}
	],
	"kind" : "codemodel",
	"paths" : 
	{
		"build" : "/home/garuda/Dev/similang-cpp/cmake-build-debug",
		"source" : "/home/garuda/Dev/similang-cpp"
	},
	"version" : 
	{
		"major" : 2,
		"minor" : 7
	}
}
